serperior/__init__.py
serperior/base_crawler.py
serperior/dantri_crawler.py
serperior-0.1.3.dist-info/licenses/LICENSE
serperior-0.1.3.dist-info/METADATA
serperior-0.1.3.dist-info/WHEEL
serperior-0.1.3.dist-info/top_level.txt
serperior-0.1.3.dist-info/RECORD
