Metadata-Version: 2.4
Name: serperior
Version: 0.1.3
Summary: crawl Vietnamese news regarding date
Author-email: "thang.-_106" <Ruanwensheng106@gmail.com>
License: MIT License
Project-URL: Homepage, https://github.com/ruanwensheng/serperior
Project-URL: Issues, https://github.com/ruanwensheng/serperior/issues
Classifier: Programming Language :: Python :: 3
Classifier: License :: OSI Approved :: MIT License
Classifier: Operating System :: OS Independent
Requires-Python: >=3.8
License-File: LICENSE
Requires-Dist: beautifulsoup4>=4.14.0
Requires-Dist: requests>=2.32.0
Requires-Dist: lxml>=6.0.0
Requires-Dist: playwright>=1.56.0
Requires-Dist: pandas>=2.3.0
Requires-Dist: numpy>=2.2.0
Dynamic: license-file
